kafka_streamer/__init__.py
kafka_streamer/client/__init__.py
kafka_streamer/client/consumer.py
kafka_streamer/client/producer.py
kafka_streamer/exceptions.py
kafka_streamer/models/__init__.py
kafka_streamer/models/avro.py
kafka_streamer/models/base.py
kafka_streamer/streamer.py
kafka_streamer/topic/__init__.py
kafka_streamer/topic/base.py
kafka_streamer/topic/datatype/__init__.py
kafka_streamer/topic/datatype/base.py
kafka_streamer/topic/datatype/byte.py
kafka_streamer/topic/datatype/schematic.py
kafka_streamer/topic/datatype/selector.py
kafka_streamer/topic/datatype/serializable.py
kafka_streamer/topic/regex.py
kafka_streamer/topic/single.py
kafka_streamer/utils.py
kafka_streamer-0.4.8.dist-info/LICENSE
kafka_streamer-0.4.8.dist-info/WHEEL
kafka_streamer-0.4.8.dist-info/METADATA
kafka_streamer-0.4.8.dist-info/RECORD
